comic_builder/__init__.py
comic_builder/__main__.py
comic_builder/argument_parser.py
comic_builder/chapter.py
comic_builder/comic.py
comic_builder/comic_builder.py
comic_builder/metadata_parser.py
comic_builder/settings.py
comic_builder/utils.py
comic_metadata/__init__.py
comic_metadata/metadata_ejector.py
comic_metadata/metadata_injector.py
kindlegen_installer/__init__.py
kindlegen_installer/__main__.py
kindlegen_installer/kindlegen_installer.py
comic_builder-0.0.42.dist-info/LICENSE
comic_builder-0.0.42.dist-info/METADATA
comic_builder-0.0.42.dist-info/WHEEL
comic_builder-0.0.42.dist-info/entry_points.txt
comic_builder-0.0.42.dist-info/top_level.txt
comic_builder-0.0.42.dist-info/RECORD
