Metadata-Version: 2.1
Name: comic-builder
Version: 0.0.42
Summary: Build e-book files from comic images
Home-page: https://github.com/eduhoribe/comic-builder
Author: Eduwardo Horibe
Author-email: eduhoribe@gmail.com
License: UNKNOWN
Keywords: comic,manga,manga-py,ebook,epub,mobi,kindle
Platform: UNKNOWN
Classifier: Programming Language :: Python :: 3
Classifier: License :: OSI Approved :: MIT License
Classifier: Operating System :: OS Independent
Requires-Python: >=3.6
Requires-Dist: KindleComicConverter (>=5.5.2)
Requires-Dist: ruamel.std.zipfile (>=0.1.0)
Requires-Dist: psutil (~=5.7.3)
